{
    "providers": [
        {
            "type": "ttf",
            "file": "adriftus:negative_spaces.ttf",
            "shift": [0.0, 0.0],
            "size": 10.0,
            "oversample": 1.0
        },
        {
            "type": "bitmap",
            "file": "adriftus:custom_gui/mod_tools/mod_ban_inv.png",
            "ascent": 17.75,
            "height": 256,
            "chars": [
                "\u1001"
            ]
        },
        {
            "type": "bitmap",
            "file": "adriftus:custom_gui/mod_tools/mod_kick_inv.png",
            "ascent": 17.75,
            "height": 256,
            "chars": [
                "\u1002"
            ]
        },
        {
            "type": "bitmap",
            "file": "adriftus:custom_gui/mod_tools/mod_inventory_inv.png",
            "ascent": 21.75,
            "height": 256,
            "chars": [
                "\u1003"
            ]
        }
    ]
}