{
	"credit": "Edited from original work by SaphieNyako for the Feywild mod",
	"ambientocclusion": false,
	"texture_size": [128, 128],
	"textures": {
		"0": "adriftus:item/entity/dwarf_mage",
		"particle": "adriftus:item/entity/dwarf_mage"
	},
	"elements": [
		{
			"name": "legs",
			"from": [10.73426, 3.85309, 5.0625],
			"to": [10.98426, 9.41559, 9.6875],
			"rotation": {"angle": 0, "axis": "z", "origin": [6.875, 9.5625, -1.625]},
			"faces": {
				"north": {"uv": [6.125, 6.25, 6.75, 6.75], "texture": "#0"},
				"east": {"uv": [1.75, 11.75, 3, 13.5], "texture": "#0"},
				"south": {"uv": [1.625, 6.375, 2.25, 6.875], "texture": "#0"},
				"west": {"uv": [6, 8.125, 7.125, 8.5], "texture": "#0"},
				"up": {"uv": [1.375, 3.375, 0.75, 2.25], "texture": "#0"},
				"down": {"uv": [2, 2.625, 1.375, 3.75], "texture": "#0"}
			}
		},
		{
			"name": "legs",
			"from": [10.73426, 3.72809, 5.0625],
			"to": [11.23426, 3.85309, 9.6875],
			"rotation": {"angle": 0, "axis": "z", "origin": [6.875, 9.5625, -1.625]},
			"faces": {
				"north": {"uv": [6.125, 6.25, 6.75, 6.75], "texture": "#0"},
				"east": {"uv": [5.625, 8.125, 6.75, 8.375], "texture": "#0"},
				"south": {"uv": [1.625, 6.375, 2.25, 6.875], "texture": "#0"},
				"west": {"uv": [4.5, 2.375, 5.625, 2.875], "texture": "#0"},
				"up": {"uv": [6.875, 8.375, 6.25, 8.125], "texture": "#0"},
				"down": {"uv": [6.75, 8.125, 6.125, 8.375], "texture": "#0"}
			}
		},
		{
			"name": "legs",
			"from": [10.73426, 3.72809, 9.6875],
			"to": [11.23426, 9.41559, 9.8125],
			"rotation": {"angle": 0, "axis": "z", "origin": [6.875, 9.5625, -1.625]},
			"faces": {
				"north": {"uv": [6.125, 8.25, 6.75, 8.375], "texture": "#0"},
				"east": {"uv": [5.375, 8.125, 6.5, 8.375], "texture": "#0"},
				"south": {"uv": [5.75, 8.125, 6.375, 8.375], "texture": "#0"},
				"west": {"uv": [4.5, 2.375, 5.625, 2.875], "texture": "#0"},
				"up": {"uv": [1.375, 3.375, 0.75, 2.25], "texture": "#0"},
				"down": {"uv": [6.625, 8.25, 6, 8.5], "texture": "#0"}
			}
		},
		{
			"name": "legs",
			"from": [10.73426, 3.72809, 4.9375],
			"to": [11.23426, 9.41559, 5.0625],
			"rotation": {"angle": 0, "axis": "z", "origin": [6.875, 9.5625, -1.625]},
			"faces": {
				"north": {"uv": [6.375, 8.125, 7, 8.375], "texture": "#0"},
				"east": {"uv": [6.125, 8.25, 7.25, 8.375], "texture": "#0"},
				"south": {"uv": [6, 8.125, 6.625, 8.375], "texture": "#0"},
				"west": {"uv": [4.5, 2.375, 5.625, 2.875], "texture": "#0"},
				"up": {"uv": [1.375, 3.375, 0.75, 2.25], "texture": "#0"},
				"down": {"uv": [6.375, 8.125, 5.75, 8.375], "texture": "#0"}
			}
		},
		{
			"name": "legs",
			"from": [6.375, 6.0625, 3.375],
			"to": [10.875, 9.375, 7.125],
			"faces": {
				"north": {"uv": [6.5, 2.625, 7.125, 3.125], "texture": "#0"},
				"east": {"uv": [7.125, 4.375, 7.625, 4.875], "texture": "#0"},
				"south": {"uv": [4.25, 6.5, 4.875, 7], "texture": "#0"},
				"west": {"uv": [7.125, 4.875, 7.625, 5.375], "texture": "#0"},
				"up": {"uv": [7.125, 4.875, 6.5, 4.375], "texture": "#0"},
				"down": {"uv": [7.125, 4.875, 6.5, 5.375], "texture": "#0"}
			}
		},
		{
			"name": "legs",
			"from": [6.3125, 6.0625, 7.875],
			"to": [10.8125, 9.5, 11.625],
			"faces": {
				"north": {"uv": [6.375, 1.625, 7, 2.125], "texture": "#0"},
				"east": {"uv": [7.125, 0.875, 7.625, 1.375], "texture": "#0"},
				"south": {"uv": [6.5, 0.875, 7.125, 1.375], "texture": "#0"},
				"west": {"uv": [3.75, 7.125, 4.25, 7.625], "texture": "#0"},
				"up": {"uv": [7.125, 2.625, 6.5, 2.125], "texture": "#0"},
				"down": {"uv": [2.875, 6.5, 2.25, 7], "texture": "#0"}
			}
		},
		{
			"name": "legs",
			"from": [4.5625, 6.0625, 5.6875],
			"to": [10.125, 7, 9.4375],
			"faces": {
				"north": {"uv": [5.625, 1.625, 6.375, 1.75], "texture": "#0"},
				"east": {"uv": [2.5, 9, 3, 9.125], "texture": "#0"},
				"south": {"uv": [8.75, 5.875, 9.5, 6], "texture": "#0"},
				"west": {"uv": [9.125, 3.5, 9.625, 3.625], "texture": "#0"},
				"up": {"uv": [6.625, 6.25, 5.875, 5.75], "texture": "#0"},
				"down": {"uv": [6.75, 0.375, 6, 0.875], "texture": "#0"}
			}
		},
		{
			"name": "leftleg",
			"from": [5.0019, 4.14392, 2.75],
			"to": [9.0644, 7.39392, 6.625],
			"rotation": {"angle": 0, "axis": "z", "origin": [1.875, 0, -2.5]},
			"faces": {
				"north": {"uv": [7.875, 2.125, 8.375, 2.5], "texture": "#0"},
				"east": {"uv": [7.875, 2.5, 8.375, 2.875], "texture": "#0"},
				"south": {"uv": [7.875, 6.125, 8.375, 6.5], "texture": "#0"},
				"west": {"uv": [7.875, 6.5, 8.375, 6.875], "texture": "#0"},
				"up": {"uv": [2, 7.75, 1.5, 7.25], "texture": "#0"},
				"down": {"uv": [3.375, 7.25, 2.875, 7.75], "texture": "#0"}
			}
		},
		{
			"name": "leftleg",
			"from": [5.125, 3.5, 3.5],
			"to": [6.4375, 5.625, 5.75],
			"faces": {
				"north": {"uv": [9.5, 4, 9.625, 4.25], "texture": "#0"},
				"east": {"uv": [3.375, 9.125, 3.625, 9.375], "texture": "#0"},
				"south": {"uv": [9.5, 4.25, 9.625, 4.5], "texture": "#0"},
				"west": {"uv": [9.125, 3.625, 9.375, 3.875], "texture": "#0"},
				"up": {"uv": [9.625, 4.75, 9.5, 4.5], "texture": "#0"},
				"down": {"uv": [4.75, 9.5, 4.625, 9.75], "texture": "#0"}
			}
		},
		{
			"name": "leftlowerleg",
			"from": [5.93376, 1.50539, 3.125],
			"to": [9.93376, 4.13039, 6.125],
			"rotation": {"angle": 0, "axis": "z", "origin": [1.875, 0, -2.5]},
			"faces": {
				"north": {"uv": [8.125, 0.375, 8.625, 0.75], "texture": "#0"},
				"east": {"uv": [6.125, 4.375, 6.5, 4.75], "texture": "#0"},
				"south": {"uv": [8.125, 0.75, 8.625, 1.125], "texture": "#0"},
				"west": {"uv": [2.5, 7.375, 2.875, 7.75], "texture": "#0"},
				"up": {"uv": [1.5, 8.5, 1, 8.125], "texture": "#0"},
				"down": {"uv": [8.625, 1.125, 8.125, 1.5], "texture": "#0"}
			}
		},
		{
			"name": "leftshoe",
			"from": [3.375, -0.0625, 2.5],
			"to": [10.0625, 0.4375, 6.5],
			"faces": {
				"north": {"uv": [8.625, 5.625, 9.5, 5.75], "texture": "#0"},
				"east": {"uv": [9.125, 6.375, 9.625, 6.5], "texture": "#0"},
				"south": {"uv": [8.75, 1.875, 9.625, 2], "texture": "#0"},
				"west": {"uv": [9.125, 7.75, 9.625, 7.875], "texture": "#0"},
				"up": {"uv": [6.375, 2.25, 5.5, 1.75], "texture": "#0"},
				"down": {"uv": [6.5, 1.125, 5.625, 1.625], "texture": "#0"}
			}
		},
		{
			"name": "leftshoe",
			"from": [3.625, 0, 2.625],
			"to": [9.9375, 2.5625, 6.3125],
			"faces": {
				"north": {"uv": [6.875, 3.75, 7.625, 4.125], "texture": "#0"},
				"east": {"uv": [3.125, 8.125, 3.625, 8.5], "texture": "#0"},
				"south": {"uv": [6.875, 5.375, 7.625, 5.75], "texture": "#0"},
				"west": {"uv": [1.75, 0, 2.25, 0.375], "texture": "#0"},
				"up": {"uv": [3.625, 6.75, 2.875, 6.25], "texture": "#0"},
				"down": {"uv": [7, 3.25, 6.25, 3.75], "texture": "#0"}
			}
		},
		{
			"name": "leftshoe",
			"from": [5.0625, 2.4375, 2.5],
			"to": [9.75, 3.3125, 6.5625],
			"rotation": {"angle": 0, "axis": "z", "origin": [1.875, 0, -2.5]},
			"faces": {
				"north": {"uv": [9, 2.5, 9.625, 2.625], "texture": "#0"},
				"east": {"uv": [0.75, 9.25, 1.25, 9.375], "texture": "#0"},
				"south": {"uv": [9, 6.5, 9.625, 6.625], "texture": "#0"},
				"west": {"uv": [9.25, 1.375, 9.75, 1.5], "texture": "#0"},
				"up": {"uv": [3.5, 7.25, 2.875, 6.75], "texture": "#0"},
				"down": {"uv": [6.75, 6.75, 6.125, 7.25], "texture": "#0"}
			}
		},
		{
			"name": "rightleg",
			"from": [5.0019, 4.14392, 8.5625],
			"to": [9.2519, 7.39392, 12.4375],
			"rotation": {"angle": 0, "axis": "z", "origin": [1.875, 0, -2.5]},
			"faces": {
				"north": {"uv": [7.75, 7.25, 8.25, 7.625], "texture": "#0"},
				"east": {"uv": [7.375, 7.75, 7.875, 8.125], "texture": "#0"},
				"south": {"uv": [7.875, 0, 8.375, 0.375], "texture": "#0"},
				"west": {"uv": [1.625, 7.875, 2.125, 8.25], "texture": "#0"},
				"up": {"uv": [1, 7.75, 0.5, 7.25], "texture": "#0"},
				"down": {"uv": [1.5, 7.25, 1, 7.75], "texture": "#0"}
			}
		},
		{
			"name": "rightleg",
			"from": [5.125, 3.5, 9.4375],
			"to": [6.4375, 5.625, 11.6875],
			"faces": {
				"north": {"uv": [9.5, 4.75, 9.625, 5], "texture": "#0"},
				"east": {"uv": [9.125, 4.125, 9.375, 4.375], "texture": "#0"},
				"south": {"uv": [5, 9.5, 5.125, 9.75], "texture": "#0"},
				"west": {"uv": [9.125, 4.375, 9.375, 4.625], "texture": "#0"},
				"up": {"uv": [9.625, 5.25, 9.5, 5], "texture": "#0"},
				"down": {"uv": [5.25, 9.5, 5.125, 9.75], "texture": "#0"}
			}
		},
		{
			"name": "rightlowerleg",
			"from": [5.93376, 1.50539, 9],
			"to": [9.87126, 4.13039, 12],
			"rotation": {"angle": 0, "axis": "z", "origin": [1.875, 0, -2.5]},
			"faces": {
				"north": {"uv": [7.875, 6.875, 8.375, 7.25], "texture": "#0"},
				"east": {"uv": [1.375, 2.25, 1.75, 2.625], "texture": "#0"},
				"south": {"uv": [7.875, 7.625, 8.375, 8], "texture": "#0"},
				"west": {"uv": [2.875, 5.875, 3.25, 6.25], "texture": "#0"},
				"up": {"uv": [8.375, 8.375, 7.875, 8], "texture": "#0"},
				"down": {"uv": [0.5, 8.125, 0, 8.5], "texture": "#0"}
			}
		},
		{
			"name": "rightshoe",
			"from": [3.375, -0.0625, 8.6875],
			"to": [9.9375, 0.4375, 12.625],
			"faces": {
				"north": {"uv": [8.75, 2.625, 9.625, 2.75], "texture": "#0"},
				"east": {"uv": [9.125, 7.875, 9.625, 8], "texture": "#0"},
				"south": {"uv": [8.75, 2.75, 9.625, 2.875], "texture": "#0"},
				"west": {"uv": [9.125, 8, 9.625, 8.125], "texture": "#0"},
				"up": {"uv": [6.5, 2.75, 5.625, 2.25], "texture": "#0"},
				"down": {"uv": [6.5, 2.75, 5.625, 3.25], "texture": "#0"}
			}
		},
		{
			"name": "rightshoe",
			"from": [3.625, 0.0625, 8.8125],
			"to": [9.8125, 2.5625, 12.4375],
			"rotation": {"angle": 0, "axis": "y", "origin": [6.71875, 1.3125, 10.625]},
			"faces": {
				"north": {"uv": [0.625, 6.875, 1.375, 7.25], "texture": "#0"},
				"east": {"uv": [2.125, 8.125, 2.625, 8.5], "texture": "#0"},
				"south": {"uv": [1.375, 6.875, 2.125, 7.25], "texture": "#0"},
				"west": {"uv": [2, 0, 2.5, 0.375], "texture": "#0"},
				"up": {"uv": [0.75, 6.625, 0, 6.125], "texture": "#0"},
				"down": {"uv": [6.875, 3.875, 6.125, 4.375], "texture": "#0"}
			}
		},
		{
			"name": "rightshoe",
			"from": [5.0625, 2.4375, 8.4375],
			"to": [9.75, 3.3125, 12.625],
			"rotation": {"angle": 0, "axis": "z", "origin": [1.875, 0, -2.5]},
			"faces": {
				"north": {"uv": [9, 2.25, 9.625, 2.375], "texture": "#0"},
				"east": {"uv": [9.25, 0, 9.75, 0.125], "texture": "#0"},
				"south": {"uv": [9, 2.375, 9.625, 2.5], "texture": "#0"},
				"west": {"uv": [9.25, 0.125, 9.75, 0.25], "texture": "#0"},
				"up": {"uv": [7.25, 6.25, 6.625, 5.75], "texture": "#0"},
				"down": {"uv": [7.375, 0, 6.75, 0.5], "texture": "#0"}
			}
		},
		{
			"name": "leftarm",
			"from": [6.0625, 12.96887, -1.67062],
			"to": [11.1875, 17.46887, 2.95438],
			"rotation": {"angle": 22.5, "axis": "x", "origin": [8.47917, 12.14595, 0.39188]},
			"faces": {
				"north": {"uv": [7.75, 1.5, 8.375, 1.875], "texture": "#0"},
				"east": {"uv": [4.125, 8.125, 4.625, 8.5], "texture": "#0"},
				"south": {"uv": [2.5, 7.75, 3.125, 8.125], "texture": "#0"},
				"west": {"uv": [8.125, 4.125, 8.625, 4.5], "texture": "#0"},
				"up": {"uv": [0.625, 7.125, 0, 6.625], "texture": "#0"},
				"down": {"uv": [4.25, 6.625, 3.625, 7.125], "texture": "#0"}
			}
		},
		{
			"name": "leftarm",
			"from": [6.6875, 9.65637, -1.10812],
			"to": [10.375, 13.34387, 2.64188],
			"rotation": {"angle": 22.5, "axis": "x", "origin": [8.47917, 12.14595, 0.39188]},
			"faces": {
				"north": {"uv": [6.75, 7.25, 7.25, 7.75], "texture": "#0"},
				"east": {"uv": [7.25, 7.25, 7.75, 7.75], "texture": "#0"},
				"south": {"uv": [7.375, 0, 7.875, 0.5], "texture": "#0"},
				"west": {"uv": [2, 7.375, 2.5, 7.875], "texture": "#0"},
				"up": {"uv": [7.875, 2.625, 7.375, 2.125], "texture": "#0"},
				"down": {"uv": [7.875, 2.625, 7.375, 3.125], "texture": "#0"}
			}
		},
		{
			"name": "leftarm",
			"from": [7.4375, 6.83137, -0.72062],
			"to": [9.625, 12.58137, 2.40438],
			"rotation": {"angle": 22.5, "axis": "x", "origin": [8.47917, 12.14595, 0.39188]},
			"faces": {
				"north": {"uv": [9.125, 4.625, 9.375, 4.875], "texture": "#0"},
				"east": {"uv": [4.5, 3.375, 4.875, 3.625], "texture": "#0"},
				"south": {"uv": [9.125, 4.875, 9.375, 5.125], "texture": "#0"},
				"west": {"uv": [2.125, 7.875, 2.5, 8.125], "texture": "#0"},
				"up": {"uv": [5.875, 5.25, 5.625, 4.875], "texture": "#0"},
				"down": {"uv": [3.875, 6.25, 3.625, 6.625], "texture": "#0"}
			}
		},
		{
			"name": "leftlowerarm",
			"from": [5.85206, 5.7995, -2.88362],
			"to": [9.53956, 8.987, 0.86638],
			"rotation": {"angle": -22.5, "axis": "z", "origin": [6.59581, 6.68387, -0.44143]},
			"faces": {
				"north": {"uv": [0, 11.25, 1.375, 12.25], "texture": "#0"},
				"east": {"uv": [0, 11.25, 1.375, 12.25], "texture": "#0"},
				"south": {"uv": [0, 11.25, 1.375, 12.25], "texture": "#0"},
				"west": {"uv": [0, 11.25, 1.375, 12.25], "texture": "#0"},
				"up": {"uv": [8.125, 1.125, 7.625, 0.625], "texture": "#0"},
				"down": {"uv": [7.875, 6.75, 7.375, 7.25], "texture": "#0"}
			}
		},
		{
			"name": "leftlowerarm",
			"from": [5.60206, 8.5495, -3.08362],
			"to": [9.78956, 8.987, 1.16638],
			"rotation": {"angle": -22.5, "axis": "z", "origin": [6.59581, 6.68387, -0.44143]},
			"faces": {
				"north": {"uv": [8.125, 4.5, 8.625, 4.875], "texture": "#0"},
				"east": {"uv": [4.625, 8.125, 5.125, 8.5], "texture": "#0"},
				"south": {"uv": [8.125, 4.875, 8.625, 5.25], "texture": "#0"},
				"west": {"uv": [5.125, 8.125, 5.625, 8.5], "texture": "#0"},
				"up": {"uv": [8.125, 1.125, 7.625, 0.625], "texture": "#0"},
				"down": {"uv": [7.875, 6.75, 7.375, 7.25], "texture": "#0"}
			}
		},
		{
			"name": "leftlowerarm",
			"from": [5.60206, 5.6745, -3.08362],
			"to": [9.78956, 6.112, 1.16638],
			"rotation": {"angle": -22.5, "axis": "z", "origin": [6.59581, 6.68387, -0.44143]},
			"faces": {
				"north": {"uv": [8.125, 4.5, 8.625, 4.875], "texture": "#0"},
				"east": {"uv": [4.625, 8.125, 5.125, 8.5], "texture": "#0"},
				"south": {"uv": [8.125, 4.875, 8.625, 5.25], "texture": "#0"},
				"west": {"uv": [5.125, 8.125, 5.625, 8.5], "texture": "#0"},
				"up": {"uv": [8.125, 1.125, 7.625, 0.625], "texture": "#0"},
				"down": {"uv": [7.875, 6.75, 7.375, 7.25], "texture": "#0"}
			}
		},
		{
			"name": "leftlowerarm",
			"from": [6.03956, 3.487, -2.77112],
			"to": [9.35206, 7.6745, 0.79138],
			"rotation": {"angle": -22.5, "axis": "z", "origin": [6.59581, 6.68387, -0.44143]},
			"faces": {
				"north": {"uv": [1.5, 8.25, 1.875, 8.75], "texture": "#0"},
				"east": {"uv": [3.75, 7.625, 4.25, 8.125], "texture": "#0"},
				"south": {"uv": [8.25, 3.5, 8.625, 4], "texture": "#0"},
				"west": {"uv": [7.625, 4.375, 8.125, 4.875], "texture": "#0"},
				"up": {"uv": [8.625, 5.75, 8.25, 5.25], "texture": "#0"},
				"down": {"uv": [8.75, 1.5, 8.375, 2], "texture": "#0"}
			}
		},
		{
			"name": "leftlowerarm",
			"from": [-1.7875, 3.425, -1.675],
			"to": [16.2125, 4.425, -0.675],
			"rotation": {"angle": 0, "axis": "z", "origin": [4.5, 10.5, -7]},
			"faces": {
				"north": {"uv": [6.5, 3.125, 8.75, 3.25], "texture": "#0"},
				"east": {"uv": [9.875, 1.5, 10, 1.625], "texture": "#0"},
				"south": {"uv": [7, 2, 9.25, 2.125], "texture": "#0"},
				"west": {"uv": [1.625, 9.875, 1.75, 10], "texture": "#0"},
				"up": {"uv": [9.25, 3.375, 7, 3.25], "texture": "#0"},
				"down": {"uv": [9.25, 3.375, 7, 3.5], "texture": "#0"}
			}
		},
		{
			"name": "leftlowerarm",
			"from": [-1.6, 2.8625, -2.3],
			"to": [-1.1, 5.05, -0.175],
			"rotation": {"angle": 0, "axis": "z", "origin": [4.5, 10.5, -7]},
			"faces": {
				"north": {"uv": [9.625, 7, 9.75, 7.25], "texture": "#0"},
				"east": {"uv": [7.625, 0.75, 7.875, 1], "texture": "#0"},
				"south": {"uv": [7.125, 9.625, 7.25, 9.875], "texture": "#0"},
				"west": {"uv": [9.25, 9, 9.5, 9.25], "texture": "#0"},
				"up": {"uv": [9.75, 7.5, 9.625, 7.25], "texture": "#0"},
				"down": {"uv": [7.75, 9.625, 7.625, 9.875], "texture": "#0"}
			}
		},
		{
			"name": "leftlowerarm",
			"from": [-5.725, 2.6625, -1.575],
			"to": [-1.225, 3.725, -0.325],
			"rotation": {"angle": 22.5, "axis": "z", "origin": [-3.85, 3.76875, -0.95]},
			"faces": {
				"north": {"uv": [13.875, 14.125, 15.625, 14.625], "texture": "#0"},
				"east": {"uv": [8.375, 9.25, 8.625, 9.5], "texture": "#0"},
				"south": {"uv": [13.875, 14.375, 15.625, 15.125], "texture": "#0"},
				"west": {"uv": [14, 14.375, 14.75, 15], "texture": "#0"},
				"up": {"uv": [15.125, 14.75, 13.375, 14], "texture": "#0"},
				"down": {"uv": [15.75, 14.125, 14, 14.875], "texture": "#0"}
			}
		},
		{
			"name": "leftlowerarm",
			"from": [-0.27478, 3.2, -1.90392],
			"to": [2.78772, 4.075, -0.96642],
			"rotation": {"angle": -22.5, "axis": "y", "origin": [0.84375, 5.7125, -12.41875]},
			"faces": {
				"north": {"uv": [13.5, 14.125, 14.75, 14.625], "texture": "#0"},
				"east": {"uv": [8.375, 9.25, 8.625, 9.5], "texture": "#0"},
				"south": {"uv": [14.5, 14.125, 15.75, 14.75], "texture": "#0"},
				"west": {"uv": [15.5, 15.25, 16, 15.75], "texture": "#0"},
				"up": {"uv": [15.625, 14.5, 14.375, 14], "texture": "#0"},
				"down": {"uv": [16, 15, 14.75, 15.375], "texture": "#0"}
			}
		},
		{
			"name": "leftlowerarm",
			"from": [-5.0625, 6.29044, 0.30552],
			"to": [-1.5625, 7.10294, 1.24302],
			"rotation": {"angle": 22.5, "axis": "x", "origin": [4.5, 10.5, -7]},
			"faces": {
				"north": {"uv": [13.625, 15, 15.25, 15.5], "texture": "#0"},
				"east": {"uv": [8.375, 9.25, 8.625, 9.5], "texture": "#0"},
				"south": {"uv": [14, 14.375, 15.625, 15], "texture": "#0"},
				"west": {"uv": [14, 14.625, 14.625, 15.375], "texture": "#0"},
				"up": {"uv": [16, 15.5, 14.375, 14.875], "texture": "#0"},
				"down": {"uv": [14.5, 14.875, 14.375, 15.125], "texture": "#0"}
			}
		},
		{
			"name": "leftlowerarm",
			"from": [-4.89508, 3.55455, -1.39134],
			"to": [-1.27008, 4.80455, 0.10866],
			"rotation": {"angle": 22.5, "axis": "y", "origin": [-3.08258, 4.17955, -0.64134]},
			"faces": {
				"north": {"uv": [13.375, 14.25, 15, 15.125], "texture": "#0"},
				"east": {"uv": [8.375, 9.25, 8.625, 9.5], "texture": "#0"},
				"south": {"uv": [13.875, 14, 15.5, 14.875], "texture": "#0"},
				"west": {"uv": [13.375, 14.375, 14.125, 15.125], "texture": "#0"},
				"up": {"uv": [15, 15.25, 13.375, 14.375], "texture": "#0"},
				"down": {"uv": [15, 14, 13.375, 14.875], "texture": "#0"}
			}
		},
		{
			"name": "leftlowerarm",
			"from": [5.85, 3.8625, -1.7375],
			"to": [6.35, 4.9875, -0.6125],
			"rotation": {"angle": 0, "axis": "z", "origin": [4.5, 10.5, -7]},
			"faces": {
				"north": {"uv": [9.875, 4.875, 10, 5], "texture": "#0"},
				"east": {"uv": [5, 9.875, 5.125, 10], "texture": "#0"},
				"south": {"uv": [9.875, 5, 10, 5.125], "texture": "#0"},
				"west": {"uv": [5.125, 9.875, 5.25, 10], "texture": "#0"},
				"up": {"uv": [10, 5.25, 9.875, 5.125], "texture": "#0"},
				"down": {"uv": [5.375, 9.875, 5.25, 10], "texture": "#0"}
			}
		},
		{
			"name": "leftlowerarm",
			"from": [15.8375, 3.3625, -1.7375],
			"to": [16.3375, 4.4875, -0.6125],
			"rotation": {"angle": 0, "axis": "z", "origin": [4.5, 10.5, -7]},
			"faces": {
				"north": {"uv": [9.875, 5.25, 10, 5.375], "texture": "#0"},
				"east": {"uv": [5.375, 9.875, 5.5, 10], "texture": "#0"},
				"south": {"uv": [9.875, 5.375, 10, 5.5], "texture": "#0"},
				"west": {"uv": [5.5, 9.875, 5.625, 10], "texture": "#0"},
				"up": {"uv": [10, 5.625, 9.875, 5.5], "texture": "#0"},
				"down": {"uv": [5.75, 9.875, 5.625, 10], "texture": "#0"}
			}
		},
		{
			"name": "leftlowerarm",
			"from": [16.3375, 3.1125, -2.1125],
			"to": [17.4625, 4.675, -0.3],
			"rotation": {"angle": 0, "axis": "z", "origin": [4.5, 10.5, -7]},
			"faces": {
				"north": {"uv": [6.75, 9.625, 6.875, 9.875], "texture": "#0"},
				"east": {"uv": [7.25, 9.25, 7.5, 9.5], "texture": "#0"},
				"south": {"uv": [9.625, 6.75, 9.75, 7], "texture": "#0"},
				"west": {"uv": [8, 9.25, 8.25, 9.5], "texture": "#0"},
				"up": {"uv": [7, 9.875, 6.875, 9.625], "texture": "#0"},
				"down": {"uv": [7.125, 9.625, 7, 9.875], "texture": "#0"}
			}
		},
		{
			"name": "leftlowerarm",
			"from": [13.3375, 3.3625, -1.7375],
			"to": [13.8375, 4.4875, -0.6125],
			"rotation": {"angle": 0, "axis": "z", "origin": [4.5, 10.5, -7]},
			"faces": {
				"north": {"uv": [9.875, 6, 10, 6.125], "texture": "#0"},
				"east": {"uv": [6.125, 9.875, 6.25, 10], "texture": "#0"},
				"south": {"uv": [9.875, 6.125, 10, 6.25], "texture": "#0"},
				"west": {"uv": [6.25, 9.875, 6.375, 10], "texture": "#0"},
				"up": {"uv": [10, 6.375, 9.875, 6.25], "texture": "#0"},
				"down": {"uv": [6.5, 9.875, 6.375, 10], "texture": "#0"}
			}
		},
		{
			"name": "leftlowerarm",
			"from": [12.15, 3.3625, -1.7375],
			"to": [12.65, 4.4875, -0.6125],
			"rotation": {"angle": 0, "axis": "z", "origin": [4.5, 10.5, -7]},
			"faces": {
				"north": {"uv": [9, 7.125, 9.125, 7.25], "texture": "#0"},
				"east": {"uv": [6.5, 9.875, 6.625, 10], "texture": "#0"},
				"south": {"uv": [9.875, 6.5, 10, 6.625], "texture": "#0"},
				"west": {"uv": [4, 9, 4.125, 9.125], "texture": "#0"},
				"up": {"uv": [10, 6.75, 9.875, 6.625], "texture": "#0"},
				"down": {"uv": [6.875, 9.875, 6.75, 10], "texture": "#0"}
			}
		},
		{
			"name": "leftlowerarm",
			"from": [-1.1625, 3.3625, -1.7375],
			"to": [-0.6625, 4.4875, -0.6125],
			"rotation": {"angle": 0, "axis": "z", "origin": [4.5, 10.5, -7]},
			"faces": {
				"north": {"uv": [9.875, 6.375, 10, 6.5], "texture": "#0"},
				"east": {"uv": [6.5, 9.875, 6.625, 10], "texture": "#0"},
				"south": {"uv": [9.875, 6.5, 10, 6.625], "texture": "#0"},
				"west": {"uv": [6.625, 9.875, 6.75, 10], "texture": "#0"},
				"up": {"uv": [10, 6.75, 9.875, 6.625], "texture": "#0"},
				"down": {"uv": [6.875, 9.875, 6.75, 10], "texture": "#0"}
			}
		},
		{
			"name": "leftlowerarm",
			"from": [14.5875, 3.3625, -1.7375],
			"to": [15.0875, 4.4875, -0.6125],
			"rotation": {"angle": 0, "axis": "z", "origin": [4.5, 10.5, -7]},
			"faces": {
				"north": {"uv": [9.875, 5.625, 10, 5.75], "texture": "#0"},
				"east": {"uv": [5.75, 9.875, 5.875, 10], "texture": "#0"},
				"south": {"uv": [9.875, 5.75, 10, 5.875], "texture": "#0"},
				"west": {"uv": [5.875, 9.875, 6, 10], "texture": "#0"},
				"up": {"uv": [10, 6, 9.875, 5.875], "texture": "#0"},
				"down": {"uv": [6.125, 9.875, 6, 10], "texture": "#0"}
			}
		},
		{
			"name": "rightarm",
			"from": [6.0625, 9.7085, 11.61419],
			"to": [11.1875, 14.021, 16.30169],
			"rotation": {"angle": -22.5, "axis": "x", "origin": [3.48332, 9.6648, 5.55848]},
			"faces": {
				"north": {"uv": [4.25, 7.75, 4.875, 8.125], "texture": "#0"},
				"east": {"uv": [4.875, 7.75, 5.5, 8.125], "texture": "#0"},
				"south": {"uv": [5.5, 7.75, 6.125, 8.125], "texture": "#0"},
				"west": {"uv": [7.75, 5.75, 8.375, 6.125], "texture": "#0"},
				"up": {"uv": [2.25, 6.375, 1.625, 5.75], "texture": "#0"},
				"down": {"uv": [2.875, 5.875, 2.25, 6.5], "texture": "#0"}
			}
		},
		{
			"name": "rightarm",
			"from": [6.6875, 6.396, 11.86419],
			"to": [10.3125, 10.2085, 15.86419],
			"rotation": {"angle": -22.5, "axis": "x", "origin": [3.48332, 9.6648, 5.55848]},
			"faces": {
				"north": {"uv": [4.25, 7.25, 4.75, 7.75], "texture": "#0"},
				"east": {"uv": [4.75, 7.25, 5.25, 7.75], "texture": "#0"},
				"south": {"uv": [5.25, 7.25, 5.75, 7.75], "texture": "#0"},
				"west": {"uv": [5.75, 7.25, 6.25, 7.75], "texture": "#0"},
				"up": {"uv": [7.75, 6.25, 7.25, 5.75], "texture": "#0"},
				"down": {"uv": [6.75, 7.25, 6.25, 7.75], "texture": "#0"}
			}
		},
		{
			"name": "rightarm",
			"from": [7.3125, 3.8585, 12.05169],
			"to": [9.5, 8.9585, 15.42669],
			"rotation": {"angle": -22.5, "axis": "x", "origin": [3.48332, 9.6648, 5.55848]},
			"faces": {
				"north": {"uv": [9.125, 5.125, 9.375, 5.375], "texture": "#0"},
				"east": {"uv": [5, 8.75, 5.375, 9], "texture": "#0"},
				"south": {"uv": [9.125, 5.375, 9.375, 5.625], "texture": "#0"},
				"west": {"uv": [8.75, 6.25, 9.125, 6.5], "texture": "#0"},
				"up": {"uv": [6.75, 0.375, 6.5, 0], "texture": "#0"},
				"down": {"uv": [9, 6.5, 8.75, 6.875], "texture": "#0"}
			}
		},
		{
			"name": "rightlowerarm",
			"from": [6.03956, 2.91665, 13.354],
			"to": [9.35206, 7.10415, 16.9165],
			"rotation": {"angle": -22.5, "axis": "z", "origin": [8.64425, 7.01665, 15.03994]},
			"faces": {
				"north": {"uv": [8.375, 2.125, 8.75, 2.625], "texture": "#0"},
				"east": {"uv": [7.625, 4.875, 8.125, 5.375], "texture": "#0"},
				"south": {"uv": [8.375, 2.625, 8.75, 3.125], "texture": "#0"},
				"west": {"uv": [0.5, 7.75, 1, 8.25], "texture": "#0"},
				"up": {"uv": [8.75, 6.25, 8.375, 5.75], "texture": "#0"},
				"down": {"uv": [8.75, 6.25, 8.375, 6.75], "texture": "#0"}
			}
		},
		{
			"name": "rightlowerarm",
			"from": [5.91456, 4.85415, 13.0415],
			"to": [9.53956, 8.16665, 17.0415],
			"rotation": {"angle": -22.5, "axis": "z", "origin": [8.64425, 7.01665, 15.03994]},
			"faces": {
				"north": {"uv": [0, 11.25, 1.375, 12.25], "texture": "#0"},
				"east": {"uv": [0, 11.25, 1.375, 12.25], "texture": "#0"},
				"south": {"uv": [0, 11.25, 1.375, 12.25], "texture": "#0"},
				"west": {"uv": [0, 11.25, 1.375, 12.25], "texture": "#0"},
				"up": {"uv": [8.125, 1, 7.625, 0.5], "texture": "#0"},
				"down": {"uv": [8.125, 1, 7.625, 1.5], "texture": "#0"}
			}
		},
		{
			"name": "rightlowerarm",
			"from": [5.66456, 7.97915, 12.7915],
			"to": [9.78956, 8.29165, 17.2915],
			"rotation": {"angle": -22.5, "axis": "z", "origin": [8.64425, 7.01665, 15.03994]},
			"faces": {
				"north": {"uv": [5.625, 8.125, 6.125, 8.5], "texture": "#0"},
				"east": {"uv": [6.125, 8.125, 6.625, 8.5], "texture": "#0"},
				"south": {"uv": [6.625, 8.125, 7.125, 8.5], "texture": "#0"},
				"west": {"uv": [7.125, 8.125, 7.625, 8.5], "texture": "#0"},
				"up": {"uv": [8.125, 1, 7.625, 0.5], "texture": "#0"},
				"down": {"uv": [8.125, 1, 7.625, 1.5], "texture": "#0"}
			}
		},
		{
			"name": "rightlowerarm",
			"from": [5.66456, 4.85415, 12.7915],
			"to": [9.78956, 5.16665, 17.2915],
			"rotation": {"angle": -22.5, "axis": "z", "origin": [8.64425, 7.01665, 15.03994]},
			"faces": {
				"north": {"uv": [5.625, 8.125, 6.125, 8.5], "texture": "#0"},
				"east": {"uv": [6.125, 8.125, 6.625, 8.5], "texture": "#0"},
				"south": {"uv": [6.625, 8.125, 7.125, 8.5], "texture": "#0"},
				"west": {"uv": [7.125, 8.125, 7.625, 8.5], "texture": "#0"},
				"up": {"uv": [8.125, 1, 7.625, 0.5], "texture": "#0"},
				"down": {"uv": [8.125, 1, 7.625, 1.5], "texture": "#0"}
			}
		},
		{
			"name": "torso",
			"from": [11.25, 9.6875, 5.65],
			"to": [13, 16.4375, 10.65],
			"rotation": {"angle": -22.5, "axis": "x", "origin": [12.5, 13.11607, 9.75]},
			"faces": {
				"north": {"uv": [13.625, 4.75, 14.25, 6.75], "texture": "#0"},
				"east": {"uv": [0, 0, 0.625, 0.84375], "texture": "#0"},
				"south": {"uv": [0, 0, 0.21875, 0.84375], "texture": "#0"},
				"west": {"uv": [0, 0, 0.625, 0.84375], "texture": "#0"},
				"up": {"uv": [13.625, 4.75, 14.25, 6.75], "texture": "#0"},
				"down": {"uv": [13.625, 4.75, 14.25, 6.75], "texture": "#0"}
			}
		},
		{
			"name": "torso",
			"from": [11.25, 9.4375, 10.65],
			"to": [13, 16.6875, 10.9],
			"rotation": {"angle": -22.5, "axis": "x", "origin": [12.5, 13.11607, 9.75]},
			"faces": {
				"north": {"uv": [13.75, 7.625, 14.125, 10.25], "texture": "#0"},
				"east": {"uv": [13.75, 7.625, 13.875, 10.375], "texture": "#0"},
				"south": {"uv": [13.75, 7.625, 14.125, 10.25], "texture": "#0"},
				"west": {"uv": [0, 0, 0.03125, 0.90625], "texture": "#0"},
				"up": {"uv": [13.75, 7.625, 14.125, 7.75], "texture": "#0"},
				"down": {"uv": [13.75, 7.625, 14.125, 7.75], "texture": "#0"}
			}
		},
		{
			"name": "torso",
			"from": [11, 12.4375, 5.15],
			"to": [13.25, 13.9375, 5.4],
			"rotation": {"angle": -22.5, "axis": "x", "origin": [12.5, 13.11607, 9.75]},
			"faces": {
				"north": {"uv": [13.875, 8.75, 14.15625, 8.9375], "texture": "#0"},
				"east": {"uv": [0, 0, 0.03125, 0.1875], "texture": "#0"},
				"south": {"uv": [0, 0, 0.28125, 0.1875], "texture": "#0"},
				"west": {"uv": [0, 0, 0.03125, 0.1875], "texture": "#0"},
				"up": {"uv": [13.75, 8.375, 14.03125, 8.40625], "texture": "#0"},
				"down": {"uv": [13.75, 8.5, 14.03125, 8.53125], "texture": "#0"}
			}
		},
		{
			"name": "torso",
			"from": [13, 9.4375, 5.4],
			"to": [13.25, 16.6875, 10.65],
			"rotation": {"angle": -22.5, "axis": "x", "origin": [12.5, 13.11607, 9.75]},
			"faces": {
				"north": {"uv": [15.625, 7.625, 15.75, 10.125], "texture": "#0"},
				"east": {"uv": [13.75, 7.625, 15.75, 10.25], "texture": "#0"},
				"south": {"uv": [13.75, 7.625, 13.875, 10.375], "texture": "#0"},
				"west": {"uv": [13.75, 7.625, 15.75, 10.125], "texture": "#0"},
				"up": {"uv": [14.75, 4.75, 14.875, 6.75], "texture": "#0"},
				"down": {"uv": [14.75, 4.75, 14.875, 6.75], "texture": "#0"}
			}
		},
		{
			"name": "torso",
			"from": [13.25, 12.4375, 5.15],
			"to": [13.5, 13.9375, 7.4],
			"rotation": {"angle": -22.5, "axis": "x", "origin": [12.5, 13.11607, 9.75]},
			"faces": {
				"north": {"uv": [13.875, 8.125, 13.90625, 8.3125], "texture": "#0"},
				"east": {"uv": [13.75, 9, 14.03125, 9.1875], "texture": "#0"},
				"south": {"uv": [0, 0, 0.03125, 0.1875], "texture": "#0"},
				"west": {"uv": [0, 0, 0.28125, 0.1875], "texture": "#0"},
				"up": {"uv": [13.875, 8.125, 13.90625, 8.40625], "texture": "#0"},
				"down": {"uv": [13.875, 8.125, 13.90625, 8.40625], "texture": "#0"}
			}
		},
		{
			"name": "torso",
			"from": [13.25, 12.1875, 6.4],
			"to": [13.75, 14.1875, 7.65],
			"rotation": {"angle": -22.5, "axis": "x", "origin": [12.5, 13.11607, 9.75]},
			"faces": {
				"north": {"uv": [4.375, 5.5, 4.4375, 5.75], "texture": "#0"},
				"east": {"uv": [4.875, 5.25, 5.125, 5.625], "texture": "#0"},
				"south": {"uv": [4.5, 5.625, 4.5625, 5.875], "texture": "#0"},
				"west": {"uv": [0, 0, 0.15625, 0.25], "texture": "#0"},
				"up": {"uv": [5, 5.5, 5.0625, 5.65625], "texture": "#0"},
				"down": {"uv": [4.75, 5.875, 4.8125, 6.03125], "texture": "#0"}
			}
		},
		{
			"name": "torso",
			"from": [11, 9.4375, 5.4],
			"to": [11.25, 16.6875, 10.65],
			"rotation": {"angle": -22.5, "axis": "x", "origin": [12.5, 13.11607, 9.75]},
			"faces": {
				"north": {"uv": [15.625, 7.625, 15.75, 10.125], "texture": "#0"},
				"east": {"uv": [13.75, 7.625, 15.75, 10.25], "texture": "#0"},
				"south": {"uv": [13.75, 7.625, 13.875, 10.375], "texture": "#0"},
				"west": {"uv": [13.75, 7.625, 15.75, 10.25], "texture": "#0"},
				"up": {"uv": [14.75, 4.75, 14.875, 6.625], "texture": "#0"},
				"down": {"uv": [14.75, 4.75, 14.875, 6.75], "texture": "#0"}
			}
		},
		{
			"name": "torso",
			"from": [5.5, 12.3125, 3.625],
			"to": [10.625, 15.625, 11.3125],
			"faces": {
				"north": {"uv": [7.625, 5.375, 8.25, 5.75], "texture": "#0"},
				"east": {"uv": [4.875, 5.875, 5.875, 6.25], "texture": "#0"},
				"south": {"uv": [1, 7.75, 1.625, 8.125], "texture": "#0"},
				"west": {"uv": [5.875, 5.375, 6.875, 5.75], "texture": "#0"},
				"up": {"uv": [0.625, 5.25, 0, 4.25], "texture": "#0"},
				"down": {"uv": [1.25, 4.375, 0.625, 5.375], "texture": "#0"}
			}
		},
		{
			"name": "torso",
			"from": [5.02161, 6.75089, 3],
			"to": [10.52161, 11.06339, 12.3125],
			"rotation": {"angle": 0, "axis": "z", "origin": [1.875, 0, -2.5]},
			"faces": {
				"north": {"uv": [6.125, 6.25, 6.75, 6.75], "texture": "#0"},
				"east": {"uv": [4.375, 1.875, 5.5, 2.375], "texture": "#0"},
				"south": {"uv": [1.625, 6.375, 2.25, 6.875], "texture": "#0"},
				"west": {"uv": [4.5, 2.375, 5.625, 2.875], "texture": "#0"},
				"up": {"uv": [1.375, 3.375, 0.75, 2.25], "texture": "#0"},
				"down": {"uv": [2, 2.625, 1.375, 3.75], "texture": "#0"}
			}
		},
		{
			"name": "torso",
			"from": [4.07584, 3.6314, 5.0625],
			"to": [4.38834, 9.1314, 9.75],
			"rotation": {"angle": 0, "axis": "z", "origin": [0.5, 8.4375, -1.375]},
			"faces": {
				"north": {"uv": [6.125, 6.25, 6.75, 6.75], "texture": "#0"},
				"east": {"uv": [6, 8.25, 6.875, 8.375], "texture": "#0"},
				"south": {"uv": [1.625, 6.375, 2.25, 6.875], "texture": "#0"},
				"west": {"uv": [1.75, 11.625, 3, 13.5], "texture": "#0"},
				"up": {"uv": [1.375, 3.375, 0.75, 2.25], "texture": "#0"},
				"down": {"uv": [2, 2.625, 1.375, 3.75], "texture": "#0"}
			}
		},
		{
			"name": "torso",
			"from": [3.95084, 3.4439, 5.0625],
			"to": [4.38834, 3.6314, 9.6875],
			"rotation": {"angle": 0, "axis": "z", "origin": [0.5, 8.4375, -1.375]},
			"faces": {
				"north": {"uv": [6.125, 6.25, 6.75, 6.75], "texture": "#0"},
				"east": {"uv": [5.5, 8.25, 6.625, 8.375], "texture": "#0"},
				"south": {"uv": [1.625, 6.375, 2.25, 6.875], "texture": "#0"},
				"west": {"uv": [5.75, 8.125, 6.875, 8.375], "texture": "#0"},
				"up": {"uv": [7, 8.5, 6.375, 8.25], "texture": "#0"},
				"down": {"uv": [6.375, 8.125, 6, 8.375], "texture": "#0"}
			}
		},
		{
			"name": "torso",
			"from": [3.95084, 3.4439, 4.9375],
			"to": [4.38834, 9.1314, 5.0625],
			"rotation": {"angle": 0, "axis": "z", "origin": [0.5, 8.4375, -1.375]},
			"faces": {
				"north": {"uv": [6.25, 8.125, 6.875, 8.375], "texture": "#0"},
				"east": {"uv": [4.375, 1.875, 5.5, 2.375], "texture": "#0"},
				"south": {"uv": [1.625, 6.375, 2.25, 6.875], "texture": "#0"},
				"west": {"uv": [5.375, 8.125, 6.5, 8.5], "texture": "#0"},
				"up": {"uv": [1.375, 3.375, 0.75, 2.25], "texture": "#0"},
				"down": {"uv": [6.5, 8.25, 5.875, 8.375], "texture": "#0"}
			}
		},
		{
			"name": "torso",
			"from": [3.95084, 3.4439, 9.6875],
			"to": [4.38834, 9.1314, 9.8125],
			"rotation": {"angle": 0, "axis": "z", "origin": [0.5, 8.4375, -1.375]},
			"faces": {
				"north": {"uv": [6.125, 8.125, 6.75, 8.25], "texture": "#0"},
				"east": {"uv": [4.375, 1.875, 5.5, 2.375], "texture": "#0"},
				"south": {"uv": [5.5, 8.25, 6.125, 8.375], "texture": "#0"},
				"west": {"uv": [4.5, 8.25, 6.5, 8.375], "texture": "#0"},
				"up": {"uv": [1.375, 3.375, 0.75, 2.25], "texture": "#0"},
				"down": {"uv": [6.875, 8.125, 6.25, 8.375], "texture": "#0"}
			}
		},
		{
			"name": "torso",
			"from": [5.52161, 11.00089, 3],
			"to": [10.52161, 12.93839, 12.3125],
			"rotation": {"angle": 0, "axis": "z", "origin": [1.875, 0, -2.5]},
			"faces": {
				"north": {"uv": [5.25, 0.375, 5.875, 0.625], "texture": "#0"},
				"east": {"uv": [6.5, 1.375, 7.625, 1.625], "texture": "#0"},
				"south": {"uv": [4.75, 8.5, 5.375, 8.75], "texture": "#0"},
				"west": {"uv": [6.875, 4.125, 8, 4.375], "texture": "#0"},
				"up": {"uv": [2.625, 3.875, 2, 2.75], "texture": "#0"},
				"down": {"uv": [3.25, 2.75, 2.625, 3.875], "texture": "#0"}
			}
		},
		{
			"name": "torso",
			"from": [4.38021, 9.36198, 2.60677],
			"to": [10.94271, 10.36198, 12.48177],
			"faces": {
				"north": {"uv": [2, 8.75, 2.82031, 8.875], "texture": "#0"},
				"east": {"uv": [0.625, 7, 1.85938, 7.125], "texture": "#0"},
				"south": {"uv": [0.875, 7, 1.69531, 7.125], "texture": "#0"},
				"west": {"uv": [0.875, 7, 2.10938, 7.125], "texture": "#0"},
				"up": {"uv": [1.875, 0.125, 2.69531, 1.35938], "texture": "#0"},
				"down": {"uv": [1.875, 0, 2.69531, 1.23438], "texture": "#0"}
			}
		},
		{
			"name": "torso",
			"from": [11.6025, 10.35125, 4.83875],
			"to": [12.3225, 10.71125, 5.55875],
			"rotation": {"angle": 0, "axis": "z", "origin": [3.1575, 22.93125, -1.82625]},
			"faces": {
				"north": {"uv": [5.25, 13.125, 5.625, 13.125], "texture": "#0"},
				"east": {"uv": [5.25, 13, 5.625, 13.125], "texture": "#0"},
				"south": {"uv": [5.25, 13, 5.625, 13.125], "texture": "#0"},
				"west": {"uv": [5.25, 13.125, 5.625, 13.25], "texture": "#0"},
				"up": {"uv": [5.25, 13, 5.625, 13.25], "texture": "#0"},
				"down": {"uv": [0, 0, 0.0625, 0.0625], "texture": "#0"}
			}
		},
		{
			"name": "torso",
			"from": [11.4225, 9.99125, 4.65875],
			"to": [12.5025, 10.35125, 5.73875],
			"rotation": {"angle": 0, "axis": "z", "origin": [3.1575, 22.93125, -1.82625]},
			"faces": {
				"north": {"uv": [4.375, 12.25, 4.75, 12.375], "texture": "#0"},
				"east": {"uv": [3.875, 12.25, 4.25, 12.5], "texture": "#0"},
				"south": {"uv": [4.625, 12.25, 5, 12.375], "texture": "#0"},
				"west": {"uv": [3.75, 12.25, 4.125, 12.375], "texture": "#0"},
				"up": {"uv": [4, 12.25, 4.375, 12.5], "texture": "#0"},
				"down": {"uv": [0, 0, 0.09375, 0.09375], "texture": "#0"}
			}
		},
		{
			"name": "torso",
			"from": [11.0625, 8.55125, 4.29875],
			"to": [12.8625, 9.99125, 6.09875],
			"rotation": {"angle": 0, "axis": "z", "origin": [3.1575, 22.93125, -1.82625]},
			"faces": {
				"north": {"uv": [3.75, 12.375, 5, 13.375], "texture": "#0"},
				"east": {"uv": [3.75, 12.375, 5, 13.375], "texture": "#0"},
				"south": {"uv": [3.75, 12.375, 5, 13.375], "texture": "#0"},
				"west": {"uv": [0, 0, 0.15625, 0.125], "texture": "#0"},
				"up": {"uv": [3.75, 12.375, 5, 13.375], "texture": "#0"},
				"down": {"uv": [3.75, 12.375, 5, 13.375], "texture": "#0"}
			}
		},
		{
			"name": "torso",
			"from": [11.0625, 8.55125, 2.21375],
			"to": [12.8625, 9.99125, 4.01375],
			"rotation": {"angle": 0, "axis": "z", "origin": [3.1575, 22.93125, -1.82625]},
			"faces": {
				"north": {"uv": [3.75, 12.375, 5, 13.375], "texture": "#0"},
				"east": {"uv": [3.75, 12.375, 5, 13.375], "texture": "#0"},
				"south": {"uv": [3.75, 12.375, 5, 13.375], "texture": "#0"},
				"west": {"uv": [3.75, 12.375, 5, 13.375], "texture": "#0"},
				"up": {"uv": [3.75, 12.375, 5, 13.375], "texture": "#0"},
				"down": {"uv": [3.75, 12.375, 5, 13.375], "texture": "#0"}
			}
		},
		{
			"name": "torso",
			"from": [11.4225, 9.99125, 2.57375],
			"to": [12.5025, 10.35125, 3.65375],
			"rotation": {"angle": 0, "axis": "z", "origin": [3.1575, 22.93125, -1.82625]},
			"faces": {
				"north": {"uv": [4.375, 12.25, 4.75, 12.375], "texture": "#0"},
				"east": {"uv": [3.875, 12.25, 4.25, 12.375], "texture": "#0"},
				"south": {"uv": [0, 0, 0.09375, 0.03125], "texture": "#0"},
				"west": {"uv": [3.75, 12.25, 4.125, 12.375], "texture": "#0"},
				"up": {"uv": [3.875, 12.25, 4.25, 12.5], "texture": "#0"},
				"down": {"uv": [0, 0, 0.09375, 0.09375], "texture": "#0"}
			}
		},
		{
			"name": "torso",
			"from": [11.6025, 10.35125, 2.75375],
			"to": [12.3225, 10.71125, 3.47375],
			"rotation": {"angle": 0, "axis": "z", "origin": [3.1575, 22.93125, -1.82625]},
			"faces": {
				"north": {"uv": [5.25, 13, 5.625, 13.25], "texture": "#0"},
				"east": {"uv": [5.25, 13, 5.625, 13.125], "texture": "#0"},
				"south": {"uv": [5.25, 13, 5.625, 13.125], "texture": "#0"},
				"west": {"uv": [5.25, 13, 5.625, 13.125], "texture": "#0"},
				"up": {"uv": [5.25, 13, 5.625, 13.25], "texture": "#0"},
				"down": {"uv": [0, 0, 0.0625, 0.0625], "texture": "#0"}
			}
		},
		{
			"name": "head",
			"from": [5.1875, 19.45, 8.5125],
			"to": [6.1875, 20.45, 10.95],
			"rotation": {"angle": 22.5, "axis": "x", "origin": [5.6875, 20.5, 10.03125]},
			"faces": {
				"north": {"uv": [7.75, 9.625, 7.875, 9.75], "texture": "#0"},
				"east": {"uv": [2.625, 9.5, 2.875, 9.625], "texture": "#0"},
				"south": {"uv": [9.625, 7.75, 9.75, 7.875], "texture": "#0"},
				"west": {"uv": [9.5, 3.25, 9.75, 3.375], "texture": "#0"},
				"up": {"uv": [8.125, 4.375, 8, 4.125], "texture": "#0"},
				"down": {"uv": [3, 9.5, 2.875, 9.75], "texture": "#0"}
			}
		},
		{
			"name": "head",
			"from": [5.1875, 19.8875, 3.9375],
			"to": [6.1875, 20.8875, 6.3125],
			"rotation": {"angle": -22.5, "axis": "x", "origin": [5.6875, 20.3875, 5.125]},
			"faces": {
				"north": {"uv": [9.625, 6, 9.75, 6.125], "texture": "#0"},
				"east": {"uv": [9.5, 1.5, 9.75, 1.625], "texture": "#0"},
				"south": {"uv": [9.625, 7.5, 9.75, 7.625], "texture": "#0"},
				"west": {"uv": [9.5, 1.625, 9.75, 1.75], "texture": "#0"},
				"up": {"uv": [0.75, 6.875, 0.625, 6.625], "texture": "#0"},
				"down": {"uv": [5.375, 7, 5.25, 7.25], "texture": "#0"}
			}
		},
		{
			"name": "head",
			"from": [4.375, 16.3125, 6.5625],
			"to": [5.875, 17.625, 8.5625],
			"faces": {
				"north": {"uv": [3.625, 2.625, 3.875, 2.75], "texture": "#0"},
				"east": {"uv": [1.75, 3.75, 2, 3.875], "texture": "#0"},
				"south": {"uv": [7.875, 0.375, 8.125, 0.5], "texture": "#0"},
				"west": {"uv": [9.375, 8.875, 9.625, 9], "texture": "#0"},
				"up": {"uv": [2.125, 8.5, 1.875, 8.25], "texture": "#0"},
				"down": {"uv": [1.375, 9, 1.125, 9.25], "texture": "#0"}
			}
		},
		{
			"name": "head",
			"from": [3.875, 9.1875, 3.3125],
			"to": [6.1875, 14.4375, 11.6875],
			"faces": {
				"north": {"uv": [3, 8.5, 3.25, 9.125], "texture": "#0"},
				"east": {"uv": [3.375, 3.875, 4.375, 4.5], "texture": "#0"},
				"south": {"uv": [3.25, 8.5, 3.5, 9.125], "texture": "#0"},
				"west": {"uv": [4.25, 0, 5.25, 0.625], "texture": "#0"},
				"up": {"uv": [7.375, 3.125, 7.125, 2.125], "texture": "#0"},
				"down": {"uv": [3.75, 7.125, 3.5, 8.125], "texture": "#0"}
			}
		},
		{
			"name": "head",
			"from": [5.1875, 16.4375, 6.125],
			"to": [6, 17.3125, 7.5],
			"faces": {
				"north": {"uv": [0.625, 4.25, 0.75, 4.375], "texture": "#0"},
				"east": {"uv": [5.5, 2.25, 5.625, 2.375], "texture": "#0"},
				"south": {"uv": [1.625, 5.625, 1.75, 5.75], "texture": "#0"},
				"west": {"uv": [6.375, 2.125, 6.5, 2.25], "texture": "#0"},
				"up": {"uv": [2.25, 7, 2.125, 6.875], "texture": "#0"},
				"down": {"uv": [0.625, 7.125, 0.5, 7.25], "texture": "#0"}
			}
		},
		{
			"name": "head",
			"from": [5.1875, 16.4375, 7.625],
			"to": [6, 17.3125, 9],
			"faces": {
				"north": {"uv": [2, 7.25, 2.125, 7.375], "texture": "#0"},
				"east": {"uv": [7.625, 1.5, 7.75, 1.625], "texture": "#0"},
				"south": {"uv": [7.75, 6.125, 7.875, 6.25], "texture": "#0"},
				"west": {"uv": [7.75, 7.625, 7.875, 7.75], "texture": "#0"},
				"up": {"uv": [1.625, 8.25, 1.5, 8.125], "texture": "#0"},
				"down": {"uv": [8.25, 5.25, 8.125, 5.375], "texture": "#0"}
			}
		},
		{
			"name": "head",
			"from": [5.875, 16, 3.4375],
			"to": [10.9375, 21.125, 11.375],
			"faces": {
				"north": {"uv": [3.25, 5.625, 3.875, 6.25], "texture": "#0"},
				"east": {"uv": [0.75, 3.75, 1.75, 4.375], "texture": "#0"},
				"south": {"uv": [5.625, 3.25, 6.25, 3.875], "texture": "#0"},
				"west": {"uv": [1.75, 3.875, 2.75, 4.5], "texture": "#0"},
				"up": {"uv": [4.5, 3.625, 3.875, 2.625], "texture": "#0"},
				"down": {"uv": [3.375, 3.875, 2.75, 4.875], "texture": "#0"}
			}
		},
		{
			"name": "head",
			"from": [5.875, 14.8125, 3.4375],
			"to": [9.5, 16.0625, 11.5],
			"faces": {
				"north": {"uv": [9.125, 3.875, 9.625, 4], "texture": "#0"},
				"east": {"uv": [4.875, 4.75, 5.875, 4.875], "texture": "#0"},
				"south": {"uv": [9.125, 6.25, 9.625, 6.375], "texture": "#0"},
				"west": {"uv": [6.5, 8.5, 7.5, 8.625], "texture": "#0"},
				"up": {"uv": [4.375, 5.5, 3.875, 4.5], "texture": "#0"},
				"down": {"uv": [3.25, 4.875, 2.75, 5.875], "texture": "#0"}
			}
		},
		{
			"name": "head",
			"from": [5, 16.4375, 6.625],
			"to": [6.1875, 18.625, 8.5],
			"faces": {
				"north": {"uv": [3.5, 0.875, 3.625, 1.125], "texture": "#0"},
				"east": {"uv": [8, 3.5, 8.25, 3.75], "texture": "#0"},
				"south": {"uv": [4.25, 0.625, 4.375, 0.875], "texture": "#0"},
				"west": {"uv": [0.75, 8.25, 1, 8.5], "texture": "#0"},
				"up": {"uv": [4.5, 2.625, 4.375, 2.375], "texture": "#0"},
				"down": {"uv": [6, 0.375, 5.875, 0.625], "texture": "#0"}
			}
		},
		{
			"name": "head",
			"from": [6.6875, 18.125, 3.0625],
			"to": [7.9375, 20.3125, 4.0625],
			"faces": {
				"north": {"uv": [5.25, 9.5, 5.375, 9.75], "texture": "#0"},
				"east": {"uv": [9.5, 5.375, 9.625, 5.625], "texture": "#0"},
				"south": {"uv": [9.5, 5.875, 9.625, 6.125], "texture": "#0"},
				"west": {"uv": [9.5, 6.875, 9.625, 7.125], "texture": "#0"},
				"up": {"uv": [8, 9.75, 7.875, 9.625], "texture": "#0"},
				"down": {"uv": [9.75, 7.875, 9.625, 8], "texture": "#0"}
			}
		},
		{
			"name": "head",
			"from": [6.6875, 18.125, 10.875],
			"to": [7.9375, 20.3125, 11.875],
			"faces": {
				"north": {"uv": [9.5, 7.125, 9.625, 7.375], "texture": "#0"},
				"east": {"uv": [7.25, 9.5, 7.375, 9.75], "texture": "#0"},
				"south": {"uv": [7.375, 9.5, 7.5, 9.75], "texture": "#0"},
				"west": {"uv": [9.5, 7.375, 9.625, 7.625], "texture": "#0"},
				"up": {"uv": [9.75, 8.125, 9.625, 8], "texture": "#0"},
				"down": {"uv": [8.375, 9.625, 8.25, 9.75], "texture": "#0"}
			}
		},
		{
			"name": "head",
			"from": [4.3875, 15.625, 5.8125],
			"to": [5.5125, 16.9375, 9.4375],
			"rotation": {"angle": -22.5, "axis": "z", "origin": [4.05, 16.28125, 7.625]},
			"faces": {
				"north": {"uv": [8.625, 1.375, 8.75, 1.5], "texture": "#0"},
				"east": {"uv": [2, 2.625, 2.5, 2.75], "texture": "#0"},
				"south": {"uv": [9.625, 5.125, 9.75, 5.25], "texture": "#0"},
				"west": {"uv": [5.625, 3.875, 6.125, 4], "texture": "#0"},
				"up": {"uv": [3.5, 7.75, 3.375, 7.25], "texture": "#0"},
				"down": {"uv": [1.5, 9, 1.375, 9.5], "texture": "#0"}
			}
		},
		{
			"name": "head",
			"from": [10.6625, 20.425, 5],
			"to": [11.7875, 21.7375, 9.5],
			"rotation": {"angle": 22.5, "axis": "z", "origin": [11.625, 21.08125, 7.25]},
			"faces": {
				"north": {"uv": [9.875, 4.375, 10, 4.5], "texture": "#0"},
				"east": {"uv": [1.875, 9.125, 2.5, 9.25], "texture": "#0"},
				"south": {"uv": [4.5, 9.875, 4.625, 10], "texture": "#0"},
				"west": {"uv": [2.5, 9.125, 3.125, 9.25], "texture": "#0"},
				"up": {"uv": [0.25, 9.625, 0.125, 9], "texture": "#0"},
				"down": {"uv": [0.375, 9, 0.25, 9.625], "texture": "#0"}
			}
		},
		{
			"name": "head",
			"from": [3.5375, 14.0125, 6.375],
			"to": [4.6625, 16.075, 8.8125],
			"rotation": {"angle": -22.5, "axis": "z", "origin": [3.575, 15.04375, 7.59375]},
			"faces": {
				"north": {"uv": [4.375, 9.625, 4.5, 9.875], "texture": "#0"},
				"east": {"uv": [1.5, 9.25, 1.75, 9.5], "texture": "#0"},
				"south": {"uv": [9.625, 4.375, 9.75, 4.625], "texture": "#0"},
				"west": {"uv": [9.25, 1.5, 9.5, 1.75], "texture": "#0"},
				"up": {"uv": [4.625, 9.875, 4.5, 9.625], "texture": "#0"},
				"down": {"uv": [9.75, 4.625, 9.625, 4.875], "texture": "#0"}
			}
		},
		{
			"name": "head",
			"from": [11.0625, 17.55, 6.0625],
			"to": [12.1875, 19.6125, 8.5],
			"rotation": {"angle": 0, "axis": "z", "origin": [6.6875, -1.0625, -2.8125]},
			"faces": {
				"north": {"uv": [6, 9.625, 6.125, 9.875], "texture": "#0"},
				"east": {"uv": [2.5, 9.25, 2.75, 9.5], "texture": "#0"},
				"south": {"uv": [6.125, 9.625, 6.25, 9.875], "texture": "#0"},
				"west": {"uv": [2.75, 9.25, 3, 9.5], "texture": "#0"},
				"up": {"uv": [6.375, 9.875, 6.25, 9.625], "texture": "#0"},
				"down": {"uv": [9.75, 6.25, 9.625, 6.5], "texture": "#0"}
			}
		},
		{
			"name": "head",
			"from": [3.5625, 9.5625, 6.375],
			"to": [3.9375, 13.0625, 8.8125],
			"faces": {
				"north": {"uv": [1.25, 9.25, 1.375, 9.75], "texture": "#0"},
				"east": {"uv": [1.5, 8.75, 1.75, 9.25], "texture": "#0"},
				"south": {"uv": [1.875, 9.25, 2, 9.75], "texture": "#0"},
				"west": {"uv": [8.75, 2.125, 9, 2.625], "texture": "#0"},
				"up": {"uv": [4.875, 9.875, 4.75, 9.625], "texture": "#0"},
				"down": {"uv": [5, 9.625, 4.875, 9.875], "texture": "#0"}
			}
		},
		{
			"name": "head",
			"from": [4.5625, 14.1875, 3.5],
			"to": [6.375, 16.0625, 11.4375],
			"faces": {
				"north": {"uv": [5, 9, 5.25, 9.25], "texture": "#0"},
				"east": {"uv": [7, 3.5, 8, 3.75], "texture": "#0"},
				"south": {"uv": [3.125, 9.125, 3.375, 9.375], "texture": "#0"},
				"west": {"uv": [4.25, 7, 5.25, 7.25], "texture": "#0"},
				"up": {"uv": [0.25, 8.125, 0, 7.125], "texture": "#0"},
				"down": {"uv": [0.5, 7.125, 0.25, 8.125], "texture": "#0"}
			}
		},
		{
			"name": "head",
			"from": [5.375, 16, 10.375],
			"to": [6.75, 20.1875, 11.5],
			"faces": {
				"north": {"uv": [5.25, 9, 5.375, 9.5], "texture": "#0"},
				"east": {"uv": [3.625, 9.125, 3.75, 9.625], "texture": "#0"},
				"south": {"uv": [5.625, 9.125, 5.75, 9.625], "texture": "#0"},
				"west": {"uv": [5.75, 9.125, 5.875, 9.625], "texture": "#0"},
				"up": {"uv": [9.75, 8.375, 9.625, 8.25], "texture": "#0"},
				"down": {"uv": [9.75, 8.375, 9.625, 8.5], "texture": "#0"}
			}
		},
		{
			"name": "head",
			"from": [7.75, 15.5, 3.125],
			"to": [11.125, 20.1875, 11.625],
			"faces": {
				"north": {"uv": [8.375, 6.75, 8.75, 7.25], "texture": "#0"},
				"east": {"uv": [4.5, 2.875, 5.625, 3.375], "texture": "#0"},
				"south": {"uv": [8.375, 7.25, 8.75, 7.75], "texture": "#0"},
				"west": {"uv": [4.875, 0.625, 6, 1.125], "texture": "#0"},
				"up": {"uv": [4.25, 6.625, 3.875, 5.5], "texture": "#0"},
				"down": {"uv": [1.625, 5.625, 1.25, 6.75], "texture": "#0"}
			}
		},
		{
			"name": "head",
			"from": [5.375, 16, 3.3125],
			"to": [6.75, 20.1875, 4.4375],
			"faces": {
				"north": {"uv": [5.875, 9.125, 6, 9.625], "texture": "#0"},
				"east": {"uv": [6.5, 9.125, 6.625, 9.625], "texture": "#0"},
				"south": {"uv": [6.625, 9.125, 6.75, 9.625], "texture": "#0"},
				"west": {"uv": [6.75, 9.125, 6.875, 9.625], "texture": "#0"},
				"up": {"uv": [8.75, 9.75, 8.625, 9.625], "texture": "#0"},
				"down": {"uv": [9.75, 8.625, 9.625, 8.75], "texture": "#0"}
			}
		},
		{
			"name": "head",
			"from": [3.9375, 8.4375, 4.4375],
			"to": [5.5, 9.375, 10.625],
			"faces": {
				"north": {"uv": [9.5, 3.375, 9.75, 3.5], "texture": "#0"},
				"east": {"uv": [8.75, 6, 9.5, 6.125], "texture": "#0"},
				"south": {"uv": [9.5, 5.25, 9.75, 5.375], "texture": "#0"},
				"west": {"uv": [8.75, 6.125, 9.5, 6.25], "texture": "#0"},
				"up": {"uv": [7.875, 8.875, 7.625, 8.125], "texture": "#0"},
				"down": {"uv": [0.75, 8.25, 0.5, 9], "texture": "#0"}
			}
		},
		{
			"name": "head",
			"from": [3.57083, 12.92813, 6.975],
			"to": [4.57083, 13.92813, 8.2875],
			"faces": {
				"north": {"uv": [9.875, 1.125, 10, 1.25], "texture": "#0"},
				"east": {"uv": [1.25, 9.875, 1.375, 10], "texture": "#0"},
				"south": {"uv": [9.875, 1.25, 10, 1.375], "texture": "#0"},
				"west": {"uv": [1.375, 9.875, 1.5, 10], "texture": "#0"},
				"up": {"uv": [10, 1.5, 9.875, 1.375], "texture": "#0"},
				"down": {"uv": [1.625, 9.875, 1.5, 10], "texture": "#0"}
			}
		},
		{
			"name": "head",
			"from": [10.95833, 19.62813, 6.6625],
			"to": [11.95833, 20.62813, 7.975],
			"rotation": {"angle": 0, "axis": "z", "origin": [6.99583, 19.42813, -1.8375]},
			"faces": {
				"north": {"uv": [9.875, 4.5, 10, 4.625], "texture": "#0"},
				"east": {"uv": [4.625, 9.875, 4.75, 10], "texture": "#0"},
				"south": {"uv": [9.875, 4.625, 10, 4.75], "texture": "#0"},
				"west": {"uv": [4.75, 9.875, 4.875, 10], "texture": "#0"},
				"up": {"uv": [10, 4.875, 9.875, 4.75], "texture": "#0"},
				"down": {"uv": [5, 9.875, 4.875, 10], "texture": "#0"}
			}
		},
		{
			"name": "head",
			"from": [5.18333, 17.49063, 8.35],
			"to": [5.18333, 18.74063, 9.6],
			"faces": {
				"north": {"uv": [0, 0, 0, 0.15625], "texture": "#0"},
				"east": {"uv": [15.125, 0.375, 15.28125, 0.53125], "texture": "#0"},
				"south": {"uv": [0, 0, 0, 0.15625], "texture": "#0"},
				"west": {"uv": [14.5, 0.625, 14.65625, 0.78125], "texture": "#0"},
				"up": {"uv": [0, 0, 0, 0.15625], "texture": "#0"},
				"down": {"uv": [0, 0, 0, 0.15625], "texture": "#0"}
			}
		},
		{
			"name": "head",
			"from": [5.18333, 17.49063, 5.5375],
			"to": [5.18333, 18.74063, 6.7875],
			"faces": {
				"north": {"uv": [0, 0, 0, 0.15625], "texture": "#0"},
				"east": {"uv": [14.375, 1.125, 14.53125, 1.28125], "texture": "#0"},
				"south": {"uv": [0, 0, 0, 0.15625], "texture": "#0"},
				"west": {"uv": [15, 0.5, 15.15625, 0.65625], "texture": "#0"},
				"up": {"uv": [0, 0, 0, 0.15625], "texture": "#0"},
				"down": {"uv": [0, 0, 0, 0.15625], "texture": "#0"}
			}
		}
	],
	"display": {
		"thirdperson_righthand": {
			"rotation": [74, -107, 0],
			"translation": [1, 3.5, -3]
		},
		"thirdperson_lefthand": {
			"rotation": [67, 77, -3],
			"translation": [0, 0.5, -3.75]
		},
		"firstperson_lefthand": {
			"rotation": [3, -180, 5],
			"translation": [2, -1, -1]
		},
		"ground": {
			"translation": [0, 3.75, 0]
		},
		"gui": {
			"rotation": [0, 89, 0],
			"translation": [1, -2.75, 0]
		},
		"head": {
			"rotation": [0, -90, 0],
			"translation": [-0.75, -18, 0],
			"scale": [1.5, 1.5, 1.5]
		},
		"fixed": {
			"rotation": [0, -90, 0],
			"translation": [-0.75, -2.25, -4.5]
		}
	},
	"groups": [
		{
			"name": "dwarf",
			"origin": [1.875, 0, -2.5],
			"rotation": [0, -90, 0],
			"color": 0,
			"children": [
				{
					"name": "legs",
					"origin": [1.875, 0, -2.5],
					"color": 1,
					"children": [
						0,
						1,
						2,
						3,
						4,
						5,
						6,
						{
							"name": "leftleg",
							"origin": [3, 7.5, -4.5],
							"color": 2,
							"children": [
								7,
								8,
								{
									"name": "leftlowerleg",
									"origin": [3, 4, -4.5],
									"color": 3,
									"children": [
										9,
										{
											"name": "leftshoe",
											"origin": [3, 2.5, -4.5],
											"color": 4,
											"children": [10, 11, 12]
										}
									]
								}
							]
						},
						{
							"name": "rightleg",
							"origin": [3, 7.5, 1.5],
							"color": 5,
							"children": [
								13,
								14,
								{
									"name": "rightlowerleg",
									"origin": [3, 4, 1.5],
									"color": 6,
									"children": [
										15,
										{
											"name": "rightshoe",
											"origin": [3, 2.5, 1.5],
											"color": 7,
											"children": [16, 17, 18]
										}
									]
								}
							]
						}
					]
				},
				{
					"name": "arms",
					"origin": [4.75, 17, -1.4375],
					"color": 8,
					"children": [
						{
							"name": "leftarm",
							"origin": [4.5, 17, -7],
							"rotation": [7.5, 0, 0],
							"color": 9,
							"children": [
								19,
								20,
								21,
								{
									"name": "leftlowerarm",
									"origin": [4.5, 10.5, -7],
									"color": 0,
									"children": [22, 23, 24, 25, 26, 27, 28, 29, 30, 31, 32, 33, 34, 35, 36, 37, 38]
								}
							]
						},
						{
							"name": "rightarm",
							"origin": [4.5, 17, 4],
							"rotation": [-7.5, 0, 0],
							"color": 1,
							"children": [
								39,
								40,
								41,
								{
									"name": "rightlowerarm",
									"origin": [4.5, 10.5, 4],
									"color": 2,
									"children": [42, 43, 44, 45]
								}
							]
						}
					]
				},
				{
					"name": "torso",
					"origin": [2.19271, 15.92448, -1.26823],
					"color": 3,
					"children": [
						46,
						47,
						48,
						49,
						50,
						51,
						52,
						53,
						54,
						55,
						56,
						57,
						58,
						59,
						60,
						61,
						62,
						63,
						64,
						65,
						66,
						{
							"name": "armor",
							"origin": [4.57812, 16.32031, -1.53125],
							"color": 4,
							"children": [
								{
									"name": "leftarmor",
									"origin": [4.57812, 16.32031, -1.53125],
									"color": 5,
									"children": [
										{
											"name": "leftcandle",
											"origin": [5.10937, 21.35156, -9.125],
											"color": 6,
											"children": []
										}
									]
								},
								{
									"name": "rightarmor",
									"origin": [4.57812, 16.32031, -1.53125],
									"color": 7,
									"children": [
										{
											"name": "rightcandle",
											"origin": [5.10937, 21.47656, 5.3125],
											"color": 8,
											"children": []
										}
									]
								}
							]
						}
					]
				},
				{
					"name": "head",
					"origin": [2.18333, 20.49063, -1.525],
					"color": 9,
					"children": [67, 68, 69, 70, 71, 72, 73, 74, 75, 76, 77, 78, 79, 80, 81, 82, 83, 84, 85, 86, 87, 88, 89, 90, 91]
				}
			]
		}
	]
}